{
  "main": {
    "id": "f83ced145abaff26",
    "type": "split",
    "children": [
      {
        "id": "04e0b1ea37cdc84d",
        "type": "tabs",
        "children": [
          {
            "id": "3935ff0ecaa0a7f3",
            "type": "leaf",
            "state": {
              "type": "markdown",
              "state": {
                "file": "C++.md",
                "mode": "source",
                "source": false
              },
              "icon": "lucide-file",
              "title": "C++"
            }
          }
        ]
      }
    ],
    "direction": "vertical"
  },
  "left": {
    "id": "0be90eee8d11ba17",
    "type": "split",
    "children": [
      {
        "id": "7fbc0ead423963fc",
        "type": "tabs",
        "children": [
          {
            "id": "3ddd48eded475fea",
            "type": "leaf",
            "state": {
              "type": "file-explorer",
              "state": {
                "sortOrder": "alphabetical",
                "autoReveal": false
              },
              "icon": "lucide-folder-closed",
              "title": "Files"
            }
          },
          {
            "id": "59fa6414b79825f4",
            "type": "leaf",
            "state": {
              "type": "search",
              "state": {
                "query": "",
                "matchingCase": false,
                "explainSearch": false,
                "collapseAll": false,
                "extraContext": false,
                "sortOrder": "alphabetical"
              },
              "icon": "lucide-search",
              "title": "Search"
            }
          },
          {
            "id": "dbb97d459d1098c3",
            "type": "leaf",
            "state": {
              "type": "bookmarks",
              "state": {},
              "icon": "lucide-bookmark",
              "title": "Bookmarks"
            }
          }
        ]
      }
    ],
    "direction": "horizontal",
    "width": 300
  },
  "right": {
    "id": "e7ec11c3fa46a3d2",
    "type": "split",
    "children": [
      {
        "id": "9d2db3c42e396a60",
        "type": "tabs",
        "children": [
          {
            "id": "dda92f6ec96f16a7",
            "type": "leaf",
            "state": {
              "type": "backlink",
              "state": {
                "file": "API Recon.md",
                "collapseAll": false,
                "extraContext": false,
                "sortOrder": "alphabetical",
                "showSearch": false,
                "searchQuery": "",
                "backlinkCollapsed": false,
                "unlinkedCollapsed": true
              },
              "icon": "links-coming-in",
              "title": "Backlinks for API Recon"
            }
          },
          {
            "id": "b4cd4a8a5b7ab7fd",
            "type": "leaf",
            "state": {
              "type": "outgoing-link",
              "state": {
                "file": "API Recon.md",
                "linksCollapsed": false,
                "unlinkedCollapsed": true
              },
              "icon": "links-going-out",
              "title": "Outgoing links from API Recon"
            }
          },
          {
            "id": "418d9a923abd904c",
            "type": "leaf",
            "state": {
              "type": "tag",
              "state": {
                "sortOrder": "frequency",
                "useHierarchy": true,
                "showSearch": false,
                "searchQuery": ""
              },
              "icon": "lucide-tags",
              "title": "Tags"
            }
          },
          {
            "id": "40789661802e32ef",
            "type": "leaf",
            "state": {
              "type": "all-properties",
              "state": {
                "sortOrder": "frequency",
                "showSearch": false,
                "searchQuery": ""
              },
              "icon": "lucide-archive",
              "title": "All properties"
            }
          },
          {
            "id": "2fc11c1329c714ea",
            "type": "leaf",
            "state": {
              "type": "outline",
              "state": {
                "file": "API Recon.md",
                "followCursor": false,
                "showSearch": false,
                "searchQuery": ""
              },
              "icon": "lucide-list",
              "title": "Outline of API Recon"
            }
          },
          {
            "id": "0f63e313994b6401",
            "type": "leaf",
            "state": {
              "type": "git-view",
              "state": {},
              "icon": "git-pull-request",
              "title": "Source Control"
            }
          }
        ],
        "currentTab": 5
      }
    ],
    "direction": "horizontal",
    "width": 300
  },
  "left-ribbon": {
    "hiddenItems": {
      "switcher:Open quick switcher": false,
      "graph:Open graph view": false,
      "canvas:Create new canvas": false,
      "daily-notes:Open today's daily note": false,
      "templates:Insert template": false,
      "command-palette:Open command palette": false,
      "bases:Create new base": false,
      "obsidian-git:Open Git source control": false
    }
  },
  "active": "3935ff0ecaa0a7f3",
  "lastOpenFiles": [
    "Yara Rules.md",
    "HackTheBox/OS fundamentals/Linux Fundamentals.md",
    "Images/Pasted image 20240716181841.png",
    "Images/Pasted image 20260503132840.png",
    "pwncollege/level 4.md",
    "pwncollege/file struct.md",
    "pwncollege/CloudSek boot2root challenge.md",
    "pwncollege/CloudSek CTF write-up.md",
    "tryhackme/Windows Forensics.md",
    "Windows privilage escalation/Foothold and initial enumeration.md",
    "C++.md",
    "Compiler Design.md",
    "devops.md",
    "External Pentest Playbook.md",
    "Sample 1 Analysis.md",
    "Reverse Engineering APIs.md",
    "CTF Infrastructure.md",
    "Images/Pasted image 20260502100342.png",
    "Images/Untitled.jpg",
    "Images/Untitled 1.jpg",
    "Malware Analysis PMAt/Dropper.DownloadfromURL.exe.md",
    "Malware Analysis PMAt/RAT.CmdSocket.exe.md",
    "Linux Privilege Escalation/Escalation Paths.md",
    "Linux Privilege Escalation/Initial enumeration.md",
    "Linux 101/Linux basics.md",
    "Linux 101/Files and filesystem.md",
    "Linux 101/intro.md",
    "Nyan Arch.md",
    "Windows privilage escalation",
    "tryhackme",
    "pwncollege/Yan85 reloaded.md",
    "pwncollege/System Exploitation 3.md",
    "pwncollege/spectre v2.md",
    "pwncollege",
    "Practical Windows Forensics",
    "Practical Ethical Hacking/Notes and kioptrix",
    "Practical Ethical Hacking/Machines",
    "Practical Ethical Hacking/Active Directory",
    "Practical Ethical Hacking/Pasted image 20240713110730.png",
    "Practical Ethical Hacking/Pasted image 20240713105557.png",
    "Practical Ethical Hacking/Pasted image 20240713105201.png",
    "Practical Ethical Hacking/Pasted image 20240712205723.png",
    "Practical Ethical Hacking/Pasted image 20240712205009.png",
    "Practical Ethical Hacking",
    "Malware Analysis PMAt",
    "Linux Privilege Escalation"
  ]
}